flatifylists/__init__.py
flatifylists-1.0.0.dist-info/LICENSE
flatifylists-1.0.0.dist-info/METADATA
flatifylists-1.0.0.dist-info/WHEEL
flatifylists-1.0.0.dist-info/top_level.txt
flatifylists-1.0.0.dist-info/RECORD
