Metadata-Version: 2.1
Name: flatifylists
Version: 1.0.0
Summary: Flatten nested Python lists into a single-depth list
Home-page: https://github.com/karishmashuklaa/flatifyLists
Author: Karishma Shukla
Author-email: karishmashuklaa@gmail.com
License: MIT
Keywords: flatten,lists,nested-lists,flatten-lists,nesting,flatify-list
Platform: UNKNOWN
Classifier: Intended Audience :: Developers
Classifier: Programming Language :: Python :: 3
Classifier: Operating System :: Unix
Classifier: Operating System :: MacOS :: MacOS X
Classifier: Operating System :: Microsoft :: Windows
License-File: LICENSE
Requires-Dist: pytest
